autorandr_rofi.py
autorandr_rofi-0.1.0.dist-info/entry_points.txt
autorandr_rofi-0.1.0.dist-info/LICENSE
autorandr_rofi-0.1.0.dist-info/WHEEL
autorandr_rofi-0.1.0.dist-info/METADATA
autorandr_rofi-0.1.0.dist-info/RECORD
